[{"model": "events.user", "pk": 1, "fields": {"password": "pbkdf2_sha256$1200000$oydPDo9rxZKLMusfuhHAxh$4Dfl8prx6/7ksvtJm3PF5E5cVmn2bjBXSsXKrvI1fo4=", "last_login": "2026-04-06T08:02:38.785Z", "is_superuser": false, "username": "dishant23", "first_name": "", "last_name": "", "email": "dishantmali23@gmail.com", "is_staff": false, "is_active": true, "date_joined": "2026-04-06T07:33:32.650Z", "groups": [], "user_permissions": []}}, {"model": "events.user", "pk": 2, "fields": {"password": "pbkdf2_sha256$1200000$Ofyz5ol7MnGAkohBPg9MAl$eW46u4O+8rayToKIj0fspf5Qv/nWyikP8hPDFoyDCBk=", "last_login": "2026-04-06T07:55:27.093Z", "is_superuser": false, "username": "Pratham", "first_name": "", "last_name": "", "email": "pratham11@gmail.com", "is_staff": false, "is_active": true, "date_joined": "2026-04-06T07:39:47.372Z", "groups": [], "user_permissions": []}}, {"model": "events.category", "pk": 1, "fields": {"name": "Music"}}, {"model": "events.category", "pk": 2, "fields": {"name": "Party"}}, {"model": "events.category", "pk": 3, "fields": {"name": "Dance"}}, {"model": "events.category", "pk": 4, "fields": {"name": "Religious"}}, {"model": "events.category", "pk": 5, "fields": {"name": "Cultural Event"}}, {"model": "events.event", "pk": 1, "fields": {"title": "New Year Party", "description": "✨🎉 New Year Party Bash 2026! 🎉✨\r\n\r\nGet ready to say goodbye to the past and welcome the future in style! Join us for an unforgettable New Year’s Eve celebration filled with music, laughter, and electrifying vibes. Dance the night away with live DJs, enjoy delicious food and drinks, and count down to midnight with a spectacular celebration you won’t forget.\r\n\r\nWhether you’re coming with friends or making new ones, this is the perfect place to create memories, share joy, and start the year on a high note. Let’s celebrate new beginnings together! 🥂✨\r\n\r\nDon’t miss the party of the year!", "organizer": "BB Events", "city": "Ahmedabad", "venue_name": "LJ Campus", "full_address": "LJ Campus, LJ University Rd, off Sarkhej - Gandhinagar Highway, Makarba, Ahmedabad,", "date": "2026-04-30", "time": "20:00:00", "end_date": "2026-05-01", "end_time": null, "price": "₹1200", "refund_policy": "No Refund", "banner": "event_banners/img_UTyuvYW.avif", "categories": [1, 2, 3], "likes": [2]}}, {"model": "events.event", "pk": 2, "fields": {"title": "Diwali Pooja", "description": "🪔✨ **Diwali Pooja Invitation** ✨🪔\r\n\r\nWith great joy and festive spirit, we invite you and your family to join us for the auspicious **Diwali Pooja** on this sacred occasion of the Festival of Lights. Let us come together to seek the blessings of Goddess Lakshmi and Lord Ganesha for prosperity, happiness, and success.\r\n\r\nThe evening will be filled with traditional rituals, devotional prayers, and the warm glow of diyas, followed by prasad and festive celebrations. Your presence will make this occasion even more special and memorable for us.\r\n\r\n📅 Date: 7th April , 2026\r\n🕖 Time: 8 AM\r\n📍 Venue: Surat\r\n\r\nWe look forward to celebrating this beautiful festival with you and your loved ones.\r\n\r\n🌟 **Let’s light up our hearts and homes together!** 🌟\r\n", "organizer": "BJP", "city": "Surat", "venue_name": "SMC", "full_address": " Muglisara, Surat, Opposite LIC Building, Gordhandas Chokhavada Marg, Surat", "date": "2026-04-07", "time": "08:00:00", "end_date": "2026-04-07", "end_time": null, "price": "Free", "refund_policy": "No Refund", "banner": "event_banners/img2_ALDLvMg.jpeg", "categories": [4, 5], "likes": [1]}}]
